AUTHORS
COPYING
MANIFEST.in
README
development.ini
orbited.cfg
setup.py
moksha/__init__.py
moksha.wsgi.egg-info/PKG-INFO
moksha.wsgi.egg-info/SOURCES.txt
moksha.wsgi.egg-info/dependency_links.txt
moksha.wsgi.egg-info/entry_points.txt
moksha.wsgi.egg-info/namespace_packages.txt
moksha.wsgi.egg-info/pbr.json
moksha.wsgi.egg-info/requires.txt
moksha.wsgi.egg-info/top_level.txt
moksha/wsgi/__init__.py
moksha/wsgi/pastetemplate.py
moksha/wsgi/distutils/__init__.py
moksha/wsgi/distutils/command.py
moksha/wsgi/ext/__init__.py
moksha/wsgi/ext/turbogears.py
moksha/wsgi/i18n/ru/LC_MESSAGES/moksha.po
moksha/wsgi/lib/__init__.py
moksha/wsgi/lib/helpers.py
moksha/wsgi/lib/utils.py
moksha/wsgi/middleware/__init__.py
moksha/wsgi/middleware/extensionpoint.py
moksha/wsgi/middleware/middleware.py
moksha/wsgi/public/__init__.py
moksha/wsgi/public/css/style.css
moksha/wsgi/public/css/ui/moksha.ui.popup.css
moksha/wsgi/public/images/Powered-by-moksha_button.png
moksha/wsgi/public/images/block.png
moksha/wsgi/public/images/error.png
moksha/wsgi/public/images/fedora-icon.png
moksha/wsgi/public/images/gears.png
moksha/wsgi/public/images/grad_blue_7x80.png
moksha/wsgi/public/images/info.png
moksha/wsgi/public/images/line.png
moksha/wsgi/public/images/moksha-icon.png
moksha/wsgi/public/images/moksha-logo-small.png
moksha/wsgi/public/images/moksha-logo.png
moksha/wsgi/public/images/ok.png
moksha/wsgi/public/images/star.png
moksha/wsgi/public/images/strype2.png
moksha/wsgi/public/images/tg_under_the_hood.png
moksha/wsgi/public/images/under_the_hood_blue.png
moksha/wsgi/public/javascript/__init__.py
moksha/wsgi/public/javascript/jquery.history.js
moksha/wsgi/public/javascript/jquery.tmpl.js
moksha/wsgi/public/javascript/ui/moksha.ui.selectable.js
moksha/wsgi/public/javascript/ui/moksha.ui.tabs.js
moksha/wsgi/templates/__init__.py
moksha/wsgi/templates/error.html
moksha/wsgi/templates/footer.mak
moksha/wsgi/templates/header.mak
moksha/wsgi/templates/index.mak
moksha/wsgi/templates/login.mak
moksha/wsgi/templates/widget.mak
moksha/wsgi/templates/widgetcontainer.mak
moksha/wsgi/templates/widgets.mak
moksha/wsgi/templates/moksha/consumer/MANIFEST.in_tmpl
moksha/wsgi/templates/moksha/consumer/README.txt_tmpl
moksha/wsgi/templates/moksha/consumer/moksha/__init__.py_tmpl
